Workbook

Sheet Read me
A1: Module 9 · Harbourview AI cost model · starter workbook
A3: Harbourview Polyclinics and all figures are fictional, for teaching. S$ = Singapore dollars.
A5: HOW TO USE THIS WORKBOOK
A6: 1. Inputs: every case figure, in blue, with its source in the case pack. Change an input and the whole model should follow.
A7: 2. Model A (medicine questions assistant) and Model C (consultation note drafter): fill every YELLOW cell with a formula that refers to Inputs.
A8: Row 6 on each model sheet is a worked example showing the expected style. Never type a result as a number.
A9: 3. Each model sheet has a price multiplier cell (C3). Set it to 0.5, 1 or 1.5 to see the price scenarios.
A10: 4. Scenarios: fill the two 3 x 3 grids of net value a month. Hint: write each cell as one formula, or copy a model sheet once per price level.
A11: 5. Levers: work out the cost per question with your chosen levers and compare it with the S$1,500 cap.
A12: 6. Checks: compares your base-case results (30% adoption, today's prices, case defaults) with the expected figures. Aim for every row to say OK.
A13: 7. Sensitivity: vary at least three assumptions per initiative from low to high and record the net value.
A15: COLOUR KEY
... A18: The shared rules are in case section 6 on the Module 9 page. You may change an assumption if you say why; keep the shared-rule result alongside.

Sheet Inputs
A1: Inputs · every figure from the case pack
A3: Input | B3: Value | C3: Unit | D3: Source in the case pack
A4: — Shared —
A5: Budget, year from 1 April | B5: 450000 | C5: S$ | D5: Case 1 · CFO rule 1
A6: Realisation rate for freed staff time | B6: 0.3 | C6: share | D6: Case 1 · CFO rule 3
A7: Medicine assistant cap: model + database a month | B7: 1500 | C7: S$ | D7: Case 1 · CFO rule 4
A8: Price scenario: lower | B8: 0.5 | C8: x | D8: Case 1 · CFO rule 5
A9: Price scenario: higher | B9: 1.5 | C9: x | D9: Case 1 · CFO rule 5
A10: Adoption scenario 1 | B10: 0.1 | C10: share | D10: CFO memo
A11: Adoption scenario 2 | B11: 0.3 | C11: share | D11: CFO memo
A12: Adoption scenario 3 | B12: 0.6 | C12: share | D12: CFO memo
A13: — Medicine questions assistant (A) —
A14: Eligible patients, nine clinics | B14: 120000 | C14: patients | D14: Case 2
A15: Questions per active user a month | B15: 1.4 | C15: questions | D15: Case 2 · pilot
A16: Input tokens: instructions (same every time) | B16: 1100 | C16: tokens | D16: Case 2 · costs
A17: Input tokens: prescription summary | B17: 400 | C17: tokens | D17: Case 2 · costs
A18: Input tokens: question and recent messages | B18: 160 | C18: tokens | D18: Case 2 · costs
A19: Input tokens: three leaflet passages | B19: 1600 | C19: tokens | D19: Case 2 · costs
A20: Output tokens per answer | B20: 250 | C20: tokens | D20: Case 2 · costs
A21: Standard model: input price per million tokens | B21: 4 | C21: S$ | D21: Case 4
A22: Standard model: output price per million tokens | B22: 20 | C22: S$ | D22: Case 4
A23: Share of answers checked by the judge | B23: 0.2 | C23: share | D23: Case 2 · costs
A24: Judge input tokens per check | B24: 1600 | C24: tokens | D24: Case 2 · costs
A25: Judge output tokens per check | B25: 60 | C25: tokens | D25: Case 2 · costs
... A37: One-off rollout cost | B37: 90000 | C37: S$ | D37: Case 2 · costs
A38: — Consultation note drafter (C) —
A39: Doctor consultations a month, all clinics | B39: 95000 | C39: consultations | D39: Case 3
A40: Patients agreeing to recording | B40: 0.85 | C40: share | D40: Case 3 · pilot
A41: Doctors | B41: 260 | C41: doctors | D41: Case 3
A42: Minutes saved per drafted note | B42: 1.5 | C42: minutes | D42: Case 3 · pilot of six volunteers; reference sites 1.0
A43: Doctor cost an hour | B43: 150 | C43: S$ | D43: Case 3
A44: Price plan: 1 = per note, 2 = per seat, 3 = per accepted note | B44: 1 | C44: choice | D44: Your choice · case 3
A45: Per note price | B45: 0.38 | C45: S$ | D45: Case 3 · plans
A46: Per seat price a month | B46: 40 | C46: S$ | D46: Case 3 · plans
A47: Minimum seats | B47: 50 | C47: seats | D47: Case 3 · plans
A48: Price per accepted note | B48: 0.65 | C48: S$ | D48: Case 3 · plans
A49: Share of drafts accepted (fewer than 20% of words changed) | B49: 0.58 | C49: share | D49: Case 3 · pilot
A50: Share of drafted notes audited | B50: 0.02 | C50: share | D50: Case 3 · costs
... A53: One-off rollout cost | B53: 260000 | C53: S$ | D53: Case 3 · costs

Sheet Model A
A1: Model A · medicine questions assistant
A3: Price multiplier for this sheet (0.5, 1 or 1.5) | C3: 1
A4: Line | B4: Unit | C4: Adoption 1 | D4: Adoption 2 | E4: Adoption 3 | F4: Hint (how the shared rule works)
A5: Adoption | B5: share | C5: =Inputs!$B$10 -> 0.1 | D5: =Inputs!$B$11 -> 0.3 | E5: =Inputs!$B$12 -> 0.6
A6: Active users | B6: users | C6: =Inputs!$B$14*C5 -> 12000 | D6: =Inputs!$B$14*D5 -> 36000 | E6: =Inputs!$B$14*E5 -> 72000 | F6: Eligible patients × adoption (worked example)
A7: Questions a month | B7: questions | F7: Active users × questions per active user
A8: Assistant cost per question | B8: S$ | F8: (input tokens × input price + output tokens × output price) ÷ 1,000,000 × price multiplier
A9: Judge cost per question | B9: S$ | F9: Share judged × judge tokens cost × price multiplier
A10: Model cost a month | B10: S$ | F10: Questions × (assistant + judge cost per question)
A11: Fixed cost a month | B11: S$ | F11: Platform + database + safety review hours × pharmacist rate
A12: Running cost a month | B12: S$ | F12: Model + fixed
A13: Pharmacist hours saved a month | B13: hours | F13: (users × calls avoided × minutes per call − questions × handover rate × minutes per reply) ÷ 60
A14: Value a month | B14: S$ | F14: First 300 hours are cash at the agency rate; beyond that, pharmacist rate × realisation; negative hours cost the agency rate
A15: Net value a month | B15: S$ | F15: Value − running cost
A16: First-year cost | B16: S$ | F16: One-off + 12 × running cost
A17: Fits the budget? | B17: yes/no | F17: Compare with the budget input
A18: Payback | B18: months | F18: One-off ÷ net value a month, only if net is positive
... A21: Running cost per active user | B21: S$ | F21: Running cost ÷ active users

Sheet Model C
A1: Model C · consultation note drafter
A3: Price multiplier for this sheet (0.5, 1 or 1.5) | C3: 1
A4: Line | B4: Unit | C4: Adoption 1 | D4: Adoption 2 | E4: Adoption 3 | F4: Hint (how the shared rule works)
A5: Adoption | B5: share | C5: =Inputs!$B$10 -> 0.1 | D5: =Inputs!$B$11 -> 0.3 | E5: =Inputs!$B$12 -> 0.6
A6: Doctors using it | B6: doctors | C6: =ROUNDUP(Inputs!$B$41*C5,0) -> 26 | D6: =ROUNDUP(Inputs!$B$41*D5,0) -> 78 | E6: =ROUNDUP(Inputs!$B$41*E5,0) -> 156 | F6: Doctors × adoption, rounded up (worked example)
A7: Drafted notes a month | B7: notes | F7: Consultations × adoption × consent rate
A8: Licence a month | B8: S$ | F8: Depends on the plan input: per note; larger of minimum seats and doctors × seat price; notes × accepted share × outcome price. × price multiplier
A9: Clinical audit a month | B9: S$ | F9: Notes × share audited × minutes ÷ 60 × doctor rate
A10: Running cost a month | B10: S$ | F10: Licence + audit + devices support
A11: Running cost per note | B11: S$ | F11: Running cost ÷ notes
A12: Doctor hours freed a month | B12: hours | F12: Notes × minutes saved ÷ 60
A13: Value a month | B13: S$ | F13: Hours × doctor rate × realisation rate (capacity, not cash)
A14: Net value a month | B14: S$ | F14: Value − running cost
A15: First-year cost | B15: S$ | F15: One-off + 12 × running cost
A16: Fits the budget? | B16: yes/no | F16: Compare with the budget input
A17: Payback | B17: months | F17: One-off ÷ net value a month, only if net is positive

Sheet Scenarios
A1: Scenarios · net value a month (S$)
A2: Rows: adoption. Columns: price multiplier. Each cell must be a formula, so the grid follows the inputs.
A4: Medicine questions assistant
A5: Adoption | B5: Price × lower | C5: Price × 1 | D5: Price × higher
A6: Multiplier | B6: =Inputs!$B$8 -> 0.5 | C6: 1 | D6: =Inputs!$B$9 -> 1.5
A7: =Inputs!$B$10 -> 0.1
A8: =Inputs!$B$11 -> 0.3
A9: =Inputs!$B$12 -> 0.6
A12: Consultation note drafter (plan as set on Inputs)
A13: Adoption | B13: Price × lower | C13: Price × 1 | D13: Price × higher
A14: Multiplier | B14: =Inputs!$B$8 -> 0.5 | C14: 1 | D14: =Inputs!$B$9 -> 1.5
A15: =Inputs!$B$10 -> 0.1
A16: =Inputs!$B$11 -> 0.3
A17: =Inputs!$B$12 -> 0.6

Sheet Levers
A1: Levers · medicine assistant cost per question
A2: Set each lever to 1 (on) or 0 (off). Fill the yellow cells with formulas. Case section 4 gives the provider terms.
A4: Lever input | B4: Value | C4: Note
A5: Cache the instructions (1/0) | B5: 0
A6: Share of questions reusing the cache | B6: 0.9
A7: Cache read price as share of input price | B7: 0.1
A8: Cache write price as share of input price | B8: 1.25
A9: Two passages instead of three (1/0) | B9: 0
A10: Cap answers at 180 tokens (1/0) | B10: 0
A11: Capped output tokens | B11: 180
A12: Route routine questions to the small model (1/0) | B12: 0
A13: Share of questions routed | B13: 0.5
A14: Small model price as share of standard | B14: 0.2
A15: Router input tokens on the small model | B15: 300
A16: Small model input price per million | B16: 0.8
A17: Run the judge as a batch at half price (1/0) | B17: 0
A19: Result | B19: Value | C19: Hint
A20: Assistant cost per question with levers | C20: Instructions (cached or not) + other input + output; then the routed share at the small model price plus the router
A21: Judge cost per question with levers | C21: Judge cost, halved if batched
A22: Total cost per question | C22: Assistant + judge
A23: Model + database a month at adoption scenario 3, today's prices | C23: Questions at scenario 3 × total cost per question + database; compare with the cap
A24: Same, prices at the higher scenario | C24: Multiply the token part by the higher price multiplier

Sheet Sensitivity
A1: Sensitivity · what swings the answer (adoption scenario 2, today's prices)
A2: Change one input at a time on Inputs, record the net value a month, then put the input back. Add your own rows.
A4: Initiative | B4: Assumption | C4: Low value | D4: Net value at low | E4: High value | F4: Net value at high | G4: Range (S$) | H4: Crosses zero?
A5: A | B5: Model price multiplier | C5: 0.5 | E5: 1.5 | G5: =IF(AND(ISNUMBER(D5),ISNUMBER(F5)),ABS(F5-D5),"") | H5: =IF(AND(ISNUMBER(D5),ISNUMBER(F5)),IF(D5*F5<0,"Yes","No"),"")
A6: A | B6: Handover rate | C6: 0.16 | E6: 0.08 | G6: =IF(AND(ISNUMBER(D6),ISNUMBER(F6)),ABS(F6-D6),"") | H6: =IF(AND(ISNUMBER(D6),ISNUMBER(F6)),IF(D6*F6<0,"Yes","No"),"")
A7: A | B7: Calls avoided per active user | C7: 0.07 | E7: 0.13 | G7: =IF(AND(ISNUMBER(D7),ISNUMBER(F7)),ABS(F7-D7),"") | H7: =IF(AND(ISNUMBER(D7),ISNUMBER(F7)),IF(D7*F7<0,"Yes","No"),"")
A8: C | B8: Minutes saved per note | C8: 1 | E8: 2 | G8: =IF(AND(ISNUMBER(D8),ISNUMBER(F8)),ABS(F8-D8),"") | H8: =IF(AND(ISNUMBER(D8),ISNUMBER(F8)),IF(D8*F8<0,"Yes","No"),"")
A9: C | B9: Realisation rate | C9: 0.1 | E9: 0.5 | G9: =IF(AND(ISNUMBER(D9),ISNUMBER(F9)),ABS(F9-D9),"") | H9: =IF(AND(ISNUMBER(D9),ISNUMBER(F9)),IF(D9*F9<0,"Yes","No"),"")
A10: C | B10: Licence price multiplier | C10: 0.5 | E10: 1.5 | G10: =IF(AND(ISNUMBER(D10),ISNUMBER(F10)),ABS(F10-D10),"") | H10: =IF(AND(ISNUMBER(D10),ISNUMBER(F10)),IF(D10*F10<0,"Yes","No"),"")

Sheet Checks
A1: Checks · base case (adoption scenario 2 = 30%, price multiplier 1, case inputs, per-note plan)
A2: Set Inputs back to the case figures and both price multipliers to 1. Every row should say OK. Expected values come from the course team's reference model.
A4: Check | B4: Your result | C4: Expected | D4: Difference | E4: Status
A5: Assistant: cost per question (assistant + judge) | B5: ='Model A'!D8+'Model A'!D9 -> 0 | C5: 0.01956 | D5: =IF(ISNUMBER(B5),B5-C5,"") -> -0.01956 | E5: =IF(NOT(ISNUMBER(B5)),"Not yet",IF(B5=0,"Not yet",IF(ABS(B5-C5)<=ABS(C5)*0.01,"OK","Check"))) -> Not yet
A6: Assistant: running cost a month | B6: ='Model A'!D12 -> 0 | C6: 5345.824 | D6: =IF(ISNUMBER(B6),B6-C6,"") | E6: =IF(NOT(ISNUMBER(B6)),"Not yet",IF(B6=0,"Not yet",IF(ABS(B6-C6)<=ABS(C6)*0.01,"OK","Check"))) -> Not yet
A7: Assistant: pharmacist hours saved a month | B7: ='Model A'!D13 -> 0 | C7: 108 | D7: =IF(ISNUMBER(B7),B7-C7,"") | E7: =IF(NOT(ISNUMBER(B7)),"Not yet",IF(B7=0,"Not yet",IF(ABS(B7-C7)<=ABS(C7)*0.01,"OK","Check"))) -> Not yet
A8: Assistant: value a month | B8: ='Model A'!D14 -> 0 | C8: 7560 | D8: =IF(ISNUMBER(B8),B8-C8,"") | E8: =IF(NOT(ISNUMBER(B8)),"Not yet",IF(B8=0,"Not yet",IF(ABS(B8-C8)<=ABS(C8)*0.01,"OK","Check"))) -> Not yet
A9: Assistant: net value a month | B9: ='Model A'!D15 -> 0 | C9: 2214.176 | D9: =IF(ISNUMBER(B9),B9-C9,"") | E9: =IF(NOT(ISNUMBER(B9)),"Not yet",IF(B9=0,"Not yet",IF(ABS(B9-C9)<=ABS(C9)*0.01,"OK","Check"))) -> Not yet
A10: Assistant: handovers a day | B10: ='Model A'!D19 -> 0 | C10: 201.6 | D10: =IF(ISNUMBER(B10),B10-C10,"") | E10: =IF(NOT(ISNUMBER(B10)),"Not yet",IF(B10=0,"Not yet",IF(ABS(B10-C10)<=ABS(C10)*0.01,"OK","Check"))) -> Not yet
A11: Drafter: drafted notes a month | B11: ='Model C'!D7 -> 0 | C11: 24225 | D11: =IF(ISNUMBER(B11),B11-C11,"") | E11: =IF(NOT(ISNUMBER(B11)),"Not yet",IF(B11=0,"Not yet",IF(ABS(B11-C11)<=ABS(C11)*0.01,"OK","Check"))) -> Not yet
A12: Drafter: licence a month (per-note plan) | B12: ='Model C'!D8 -> 0 | C12: 9205.5 | D12: =IF(ISNUMBER(B12),B12-C12,"") | E12: =IF(NOT(ISNUMBER(B12)),"Not yet",IF(B12=0,"Not yet",IF(ABS(B12-C12)<=ABS(C12)*0.01,"OK","Check"))) -> Not yet
A13: Drafter: clinical audit a month | B13: ='Model C'!D9 -> 0 | C13: 6056.25 | D13: =IF(ISNUMBER(B13),B13-C13,"") | E13: =IF(NOT(ISNUMBER(B13)),"Not yet",IF(B13=0,"Not yet",IF(ABS(B13-C13)<=ABS(C13)*0.01,"OK","Check"))) -> Not yet
A14: Drafter: value a month | B14: ='Model C'!D13 -> 0 | C14: 27253.125 | D14: =IF(ISNUMBER(B14),B14-C14,"") | E14: =IF(NOT(ISNUMBER(B14)),"Not yet",IF(B14=0,"Not yet",IF(ABS(B14-C14)<=ABS(C14)*0.01,"OK","Check"))) -> Not yet
A15: Drafter: net value a month | B15: ='Model C'!D14 -> 0 | C15: 10491.375 | D15: =IF(ISNUMBER(B15),B15-C15,"") | E15: =IF(NOT(ISNUMBER(B15)),"Not yet",IF(B15=0,"Not yet",IF(ABS(B15-C15)<=ABS(C15)*0.01,"OK","Check"))) -> Not yet
